deep_rl_box/__init__.py
deep_rl_box/agents/__init__.py
deep_rl_box/agents/a2c/__init__.py
deep_rl_box/agents/a2c/agent.py
deep_rl_box/agents/a2c/eval_agent.py
deep_rl_box/agents/a2c/run_atari.py
deep_rl_box/agents/a2c/run_classic.py
deep_rl_box/agents/actor_critic/__init__.py
deep_rl_box/agents/actor_critic/agent.py
deep_rl_box/agents/actor_critic/eval_agent.py
deep_rl_box/agents/actor_critic/run_classic.py
deep_rl_box/agents/agent57/__init__.py
deep_rl_box/agents/agent57/agent.py
deep_rl_box/agents/agent57/agent_functional.py
deep_rl_box/agents/agent57/eval_agent.py
deep_rl_box/agents/agent57/run_atari.py
deep_rl_box/agents/agent57/run_classic.py
deep_rl_box/agents/c51_dqn/__init__.py
deep_rl_box/agents/c51_dqn/agent.py
deep_rl_box/agents/c51_dqn/eval_agent.py
deep_rl_box/agents/c51_dqn/run_classic.py
deep_rl_box/agents/double_dqn/__init__.py
deep_rl_box/agents/double_dqn/agent.py
deep_rl_box/agents/double_dqn/eval_agent.py
deep_rl_box/agents/double_dqn/run_atari.py
deep_rl_box/agents/double_dqn/run_classic.py
deep_rl_box/agents/dqn/__init__.py
deep_rl_box/agents/dqn/agent.py
deep_rl_box/agents/dqn/eval_agent.py
deep_rl_box/agents/dqn/run_atari.py
deep_rl_box/agents/dqn/run_classic.py
deep_rl_box/agents/drqn/__init__.py
deep_rl_box/agents/drqn/agent.py
deep_rl_box/agents/drqn/eval_agent.py
deep_rl_box/agents/drqn/run_classic.py
deep_rl_box/agents/dueling_dqn/__init__.py
deep_rl_box/agents/dueling_dqn/agent.py
deep_rl_box/agents/dueling_dqn/eval_agent.py
deep_rl_box/agents/dueling_dqn/run_classic.py
deep_rl_box/agents/iqn/__init__.py
deep_rl_box/agents/iqn/agent.py
deep_rl_box/agents/iqn/eval_agent.py
deep_rl_box/agents/iqn/run_classic.py
deep_rl_box/agents/ngu/__init__.py
deep_rl_box/agents/ngu/agent.py
deep_rl_box/agents/ngu/eval_agent.py
deep_rl_box/agents/ngu/run.py
deep_rl_box/agents/ngu/run_atari.py
deep_rl_box/agents/ngu/run_classic.py
deep_rl_box/agents/ppo/__init__.py
deep_rl_box/agents/ppo/agent.py
deep_rl_box/agents/ppo/eval_agent.py
deep_rl_box-0.0.1.dist-info/METADATA
deep_rl_box-0.0.1.dist-info/WHEEL
deep_rl_box-0.0.1.dist-info/top_level.txt
deep_rl_box-0.0.1.dist-info/RECORD
