Metadata-Version: 2.4
Name: deep_rl_box
Version: 0.0.1
Summary: a deep reinforcement learning framework
Home-page: 
Author: Sam Zamani
Author-email: sam.zmn99@gmail.com
Classifier: Programming Language :: Python :: 3
Classifier: License :: OSI Approved :: MIT License
Classifier: Operating System :: OS Independent
Requires-Python: >=3.9
Dynamic: author
Dynamic: author-email
Dynamic: classifier
Dynamic: description
Dynamic: description-content-type
Dynamic: requires-python
Dynamic: summary
